Realtorpy/__init__.py
Realtorpy/facade.py
Realtorpy/geo.py
Realtorpy/proxy.py
Realtorpy/realtor.py
Realtorpy/realtorCa.py
Realtorpy/realtorCom.py
Realtorpy/realtorFactory.py
Realtorpy/report.py
Realtorpy/config/column_mapping_cfg.json
Realtorpy/config/column_mapping_cfg_realtor_com.json
Realtorpy/config/graphql_queries.yml
Realtorpy-1.0.0.dist-info/LICENSE.md
Realtorpy-1.0.0.dist-info/METADATA
Realtorpy-1.0.0.dist-info/WHEEL
Realtorpy-1.0.0.dist-info/top_level.txt
Realtorpy-1.0.0.dist-info/RECORD
