Metadata-Version: 2.1
Name: Realtorpy
Version: 1.0.0
Summary: Python package for fetching and analyzing REALTOR.CA and REALTOR.COM MLS Listings
Home-page: https://github.com/labi1240/Realtorpy
Author: Lovepreet Gill
Author-email: labi1240@gmail.com
License: MIT
Classifier: Programming Language :: Python :: 3
Classifier: Operating System :: OS Independent
Classifier: License :: OSI Approved :: MIT License
Requires-Python: >=3.6
License-File: LICENSE.md
Requires-Dist: requests >=2.26.0
Requires-Dist: pandas >=1.3.5
Requires-Dist: numpy >=1.21.4
Requires-Dist: openpyxl >=3.1.2
Requires-Dist: lxml >=5.1.0
Requires-Dist: pyyaml >=6.0.1
Provides-Extra: dev
Requires-Dist: twine ; extra == 'dev'
